python_bpm/__init__.py
python_bpm/app.py
python_bpm/bpm_detection.py
bpm_renamer-0.4.0.dist-info/entry_points.txt
bpm_renamer-0.4.0.dist-info/WHEEL
bpm_renamer-0.4.0.dist-info/METADATA
bpm_renamer-0.4.0.dist-info/RECORD
