Metadata-Version: 2.1
Name: bpm-renamer
Version: 0.4.0
Summary: 
Author: Bruce Collie
Author-email: brucecollie82@gmail.com
Requires-Python: >=3.6,<3.12
Classifier: Programming Language :: Python :: 3
Classifier: Programming Language :: Python :: 3.6
Classifier: Programming Language :: Python :: 3.7
Classifier: Programming Language :: Python :: 3.8
Classifier: Programming Language :: Python :: 3.9
Classifier: Programming Language :: Python :: 3.10
Requires-Dist: PyWavelets (>=1.4.1,<2.0.0)
Requires-Dist: numpy (>=1.24.1,<2.0.0)
Requires-Dist: scipy (>=1.10.0,<2.0.0)
